Instruction_Fetch/ifIdLatch.v
module ifIdLatch(
    input wire clk,
    input wire rst,
    input wire [31:0] pc_in,
    input wire [31:0] instr_in,
    output reg [31:0] pc_out,
    output reg [31:0] instr_out
);
    always @(posedge clk) begin
        if (rst) begin
            pc_out <= 32'b0; 
            instr_out <= 32'b0; 
        end else begin
            pc_out <= pc_in; // pass through pc+4
            instr_out <= instr_in; //pass through instr. from instr. mem
        end
    end
endmodule

Instruction_Fetch/instrMem.v
module instrMem (
    input  wire [31:0] addr,
    output wire  [31:0] data
);
    reg [31:0] mem [0:9]; // array of 10 words, each 32 bits wide

    wire [31:0] word_index; // wire to index into mem
    assign word_index = addr[31:2];  // divide by 4 to obtain correct index

    initial begin
        mem[0] = 32'hA00000AA; 
        mem[1] = 32'h10000011; 
        mem[2] = 32'h20000022; 
        mem[3] = 32'h30000033;
        mem[4] = 32'h40000044; 
        mem[5] = 32'h50000055; 
        mem[6] = 32'h60000066; 
        mem[7] = 32'h70000077; 
        mem[8] = 32'h80000088; 
        mem[9] = 32'h90000099; 
    end

assign data = mem[addr[31:2]]; //read instruction using word index (byte address/4)

endmodule

Instruction_Fetch/incrementer.v
module incrementer(
input wire [31:0] pc_in,
output wire [31:0] pc_out
);

assign pc_out = pc_in + 32'd4; // increment pc by 4 (byte addressed)
endmodule

Instruction_Fetch/pc.v
module pc(
input wire clk,
input wire rst,
input wire [31:0] pc_in,
output reg [31:0] pc_out
);
always @(posedge clk) begin
    if (rst)
        pc_out <= 32'd0; //clear on async reset
    else
        pc_out <= pc_in; // pass pc value through to output
end
endmodule

Instruction_Fetch/mux.v
module mux (
    input wire [31:0] a_true,  
    input wire [31:0] b_false, 
    input wire sel,           
    output wire [31:0] y       
);
    assign y = (sel) ? a_true : b_false; // if PCSrc=1 choose ex_mem_npc, else choose next_pc

endmodule

Instruction_Fetch/fetch.v
module fetch (
    input  wire        clk,
    input  wire        rst,
    input  wire        ex_mem_pc_src,
    input  wire [31:0] ex_mem_npc,
    output wire [31:0] if_id_instr,
    output wire [31:0] if_id_npc
);
    // internal wires
    wire [31:0] pc_out;
    wire [31:0] pc_mux;
    wire [31:0] next_pc;
    wire [31:0] instr_data;
    
    mux m0 (
        .y(pc_mux),
        .a_true(ex_mem_npc),
        .b_false(next_pc),
        .sel(ex_mem_pc_src)
    );

    pc pc0 (
        .clk(clk),
        .rst(rst),
        .pc_in(pc_mux),
        .pc_out(pc_out)
    );

    incrementer in0 (
        .pc_in(pc_out),
        .pc_out(next_pc)
    );


    instrMem inMem0 (
        .addr(pc_out),
        .data(instr_data)
    );

    ifIdLatch ifIdLatch0 (
        .clk(clk),
        .rst(rst),
        .pc_in(next_pc),       
        .instr_in(instr_data),
        .pc_out(if_id_npc),
        .instr_out(if_id_instr)
    );

endmodule

Instruction_Fetch/fetch_tb.v
`timescale 1ns/1ps

module fetch_tb;

    reg clk;
    reg rst;
    reg ex_mem_pc_src;
    reg [31:0] ex_mem_npc;
    wire [31:0] if_id_instr;
    wire [31:0] if_id_npc;

    fetch dut (
        .clk(clk),
        .rst(rst),
        .ex_mem_pc_src(ex_mem_pc_src),
        .ex_mem_npc(ex_mem_npc),
        .if_id_instr(if_id_instr),
        .if_id_npc(if_id_npc)
    );
    initial begin
        clk = 0;
        forever #5 clk = ~clk; // 100MHz clock
    end

    initial begin
        $dumpfile("fetch_tb.vcd");
        $dumpvars(0, fetch_tb);

        rst = 1; // assert reset
        ex_mem_pc_src = 0;
        ex_mem_npc = 32'd0;

        #12;
        rst = 0; // reset off 

        #40;

        ex_mem_pc_src = 1; // PCSrc high
        ex_mem_npc = 32'd4; // branch address
        #10;

        ex_mem_pc_src = 0; // PCSrc Low
        #40;

        $finish;
    end

endmodule

Instruction_Fetch/fetch_tb.vcd
$date
	Fri Mar 20 18:49:11 2026
$end
$version
	Icarus Verilog
$end
$timescale
	1ps
$end
$scope module fetch_tb $end
$var wire 32 ! if_id_npc [31:0] $end
$var wire 32 " if_id_instr [31:0] $end
$var reg 1 # clk $end
$var reg 32 $ ex_mem_npc [31:0] $end
$var reg 1 % ex_mem_pc_src $end
$var reg 1 & rst $end
$scope module dut $end
$var wire 1 # clk $end
$var wire 32 ' ex_mem_npc [31:0] $end
$var wire 1 % ex_mem_pc_src $end
$var wire 1 & rst $end
$var wire 32 ( pc_out [31:0] $end
$var wire 32 ) pc_mux [31:0] $end
$var wire 32 * next_pc [31:0] $end
$var wire 32 + instr_data [31:0] $end
$var wire 32 , if_id_npc [31:0] $end
$var wire 32 - if_id_instr [31:0] $end
$scope module ifIdLatch0 $end
$var wire 1 # clk $end
$var wire 1 & rst $end
$var wire 32 . pc_in [31:0] $end
$var wire 32 / instr_in [31:0] $end
$var reg 32 0 instr_out [31:0] $end
$var reg 32 1 pc_out [31:0] $end
$upscope $end
$scope module in0 $end
$var wire 32 2 pc_out [31:0] $end
$var wire 32 3 pc_in [31:0] $end
$upscope $end
$scope module inMem0 $end
$var wire 32 4 data [31:0] $end
$var wire 32 5 word_index [31:0] $end
$var wire 32 6 addr [31:0] $end
$upscope $end
$scope module m0 $end
$var wire 32 7 a_true [31:0] $end
$var wire 32 8 b_false [31:0] $end
$var wire 1 % sel $end
$var wire 32 9 y [31:0] $end
$upscope $end
$scope module pc0 $end
$var wire 1 # clk $end
$var wire 32 : pc_in [31:0] $end
$var wire 1 & rst $end
$var reg 32 ; pc_out [31:0] $end
$upscope $end
$upscope $end
$upscope $end
$enddefinitions $end
$comment Show the parameter values. $end
$dumpall
$end
#0
$dumpvars
bx ;
bx :
bx 9
bx 8
b0 7
bx 6
b0xxxxxxxxxxxxxxxxxxxxxxxxxxxxxx 5
bx 4
bx 3
bx 2
bx 1
bx 0
bx /
bx .
bx -
bx ,
bx +
bx *
bx )
bx (
b0 '
1&
0%
b0 $
0#
bx "
bx !
$end
#5000
b10100000000000000000000010101010 +
b10100000000000000000000010101010 /
b10100000000000000000000010101010 4
b0 5
b100 )
b100 9
b100 :
b100 *
b100 .
b100 2
b100 8
b0 (
b0 3
b0 6
b0 ;
b0 "
b0 -
b0 0
b0 !
b0 ,
b0 1
1#
#10000
0#
#12000
0&
#15000
b10000000000000000000000010001 +
b10000000000000000000000010001 /
b10000000000000000000000010001 4
b1 5
b1000 )
b1000 9
b1000 :
b10100000000000000000000010101010 "
b10100000000000000000000010101010 -
b10100000000000000000000010101010 0
b100 !
b100 ,
b100 1
b1000 *
b1000 .
b1000 2
b1000 8
b100 (
b100 3
b100 6
b100 ;
1#
#20000
0#
#25000
b100000000000000000000000100010 +
b100000000000000000000000100010 /
b100000000000000000000000100010 4
b10 5
b1100 )
b1100 9
b1100 :
b1100 *
b1100 .
b1100 2
b1100 8
b1000 (
b1000 3
b1000 6
b1000 ;
b10000000000000000000000010001 "
b10000000000000000000000010001 -
b10000000000000000000000010001 0
b1000 !
b1000 ,
b1000 1
1#
#30000
0#
#35000
b110000000000000000000000110011 +
b110000000000000000000000110011 /
b110000000000000000000000110011 4
b11 5
b10000 )
b10000 9
b10000 :
b100000000000000000000000100010 "
b100000000000000000000000100010 -
b100000000000000000000000100010 0
b1100 !
b1100 ,
b1100 1
b10000 *
b10000 .
b10000 2
b10000 8
b1100 (
b1100 3
b1100 6
b1100 ;
1#
#40000
0#
#45000
b1000000000000000000000001000100 +
b1000000000000000000000001000100 /
b1000000000000000000000001000100 4
b100 5
b10100 )
b10100 9
b10100 :
b10100 *
b10100 .
b10100 2
b10100 8
b10000 (
b10000 3
b10000 6
b10000 ;
b110000000000000000000000110011 "
b110000000000000000000000110011 -
b110000000000000000000000110011 0
b10000 !
b10000 ,
b10000 1
1#
#50000
0#
#52000
b100 )
b100 9
b100 :
b100 $
b100 '
b100 7
1%
#55000
b10000000000000000000000010001 +
b10000000000000000000000010001 /
b10000000000000000000000010001 4
b1 5
b1000000000000000000000001000100 "
b1000000000000000000000001000100 -
b1000000000000000000000001000100 0
b10100 !
b10100 ,
b10100 1
b1000 *
b1000 .
b1000 2
b1000 8
b100 (
b100 3
b100 6
b100 ;
1#
#60000
0#
#62000
b1000 )
b1000 9
b1000 :
0%
#65000
b100000000000000000000000100010 +
b100000000000000000000000100010 /
b100000000000000000000000100010 4
b10 5
b1100 )
b1100 9
b1100 :
b1100 *
b1100 .
b1100 2
b1100 8
b1000 (
b1000 3
b1000 6
b1000 ;
b10000000000000000000000010001 "
b10000000000000000000000010001 -
b10000000000000000000000010001 0
b1000 !
b1000 ,
b1000 1
1#
#70000
0#
#75000
b110000000000000000000000110011 +
b110000000000000000000000110011 /
b110000000000000000000000110011 4
b11 5
b10000 )
b10000 9
b10000 :
b100000000000000000000000100010 "
b100000000000000000000000100010 -
b100000000000000000000000100010 0
b1100 !
b1100 ,
b1100 1
b10000 *
b10000 .
b10000 2
b10000 8
b1100 (
b1100 3
b1100 6
b1100 ;
1#
#80000
0#
#85000
b1000000000000000000000001000100 +
b1000000000000000000000001000100 /
b1000000000000000000000001000100 4
b100 5
b10100 )
b10100 9
b10100 :
b10100 *
b10100 .
b10100 2
b10100 8
b10000 (
b10000 3
b10000 6
b10000 ;
b110000000000000000000000110011 "
b110000000000000000000000110011 -
b110000000000000000000000110011 0
b10000 !
b10000 ,
b10000 1
1#
#90000
0#
#95000
b1010000000000000000000001010101 +
b1010000000000000000000001010101 /
b1010000000000000000000001010101 4
b101 5
b11000 )
b11000 9
b11000 :
b1000000000000000000000001000100 "
b1000000000000000000000001000100 -
b1000000000000000000000001000100 0
b10100 !
b10100 ,
b10100 1
b11000 *
b11000 .
b11000 2
b11000 8
b10100 (
b10100 3
b10100 6
b10100 ;
1#
